{"description":"Traceroute5840 UDP from 4061 to 196.28.224.21 (as is)","af":4,"interval":86400,"spread":null,"is_oneoff":true,"is_public":true,"resolve_on_probe":false,"start_time":1444836160,"stop_time":1444836605,"creation_time":1444836160,"resolved_ips":["213.242.116.74"],"status":{"id":4,"name":"Stopped"},"participant_count":1,"response_timeout":4000,"protocol":"UDP","paris":0,"packets":3,"size":48,"probes":[{"url":"/api/v1/probe/4061/","id":4061}],"probe_sources":[{"requested":1,"type":"probes","value":[4061]}],"type":{"id":2,"name":"traceroute","af":4},"result":"/api/v1/measurement/2812059/result/","all_scheduling_requests_fulfilled":true,"dst_addr":"213.242.116.74","dst_name":"213.242.116.74","dst_asn":3356,"msm_id":2812059,"maxhops":32,"firsthop":1}