{"af":4,"dst_addr":"41.63.1.2","dst_asn":37532,"dst_name":"41.63.1.2","msm_id":2804215,"description":"Traceroute1733 UDP from 3461 to 41.63.1.2 (full)","is_oneoff":true,"is_public":true,"interval":86400,"creation_time":1444753626,"resolve_on_probe":false,"start_time":1444753626,"stop_time":1444754103,"status":{"id":6,"name":"No suitable probes"},"resolved_ips":["41.63.1.2"],"participant_count":0,"response_timeout":4000,"protocol":"UDP","paris":0,"packets":3,"firsthop":1,"maxhops":32,"size":48,"probes":[],"probe_sources":[{"requested":1,"type":"probes","value":[3461]}],"type":{"id":2,"name":"traceroute","af":4},"result":"/api/v1/measurement/2804215/result/","can_visualise":true,"all_scheduling_requests_fulfilled":true}