[{"latency": 149.71699999999998, "msm_id": 2493068, "from": "41.204.160.27", "dst_name": "130.117.51.234", "dst_asn": 174, "timestamp": 1444337614, "proto": "UDP", "src_asn": 36914, "dst_addr": "130.117.51.234", "prb_id": 13218, "result": [{"result": {"from": "149.11.38.189", "country": "US", "coordinates": [38.0, -97.0], "public": true, "rtt": 147.89433333333332, "asn": 174}, "hop": 4}, {"result": {"from": "154.54.74.93", "country": "US", "coordinates": [38.0, -97.0], "public": true, "rtt": 147.955, "asn": 174}, "hop": 5}, {"result": {"from": "130.117.51.41", "country": "EU", "coordinates": [47.0, 8.0], "public": true, "rtt": 148.665, "asn": 174}, "hop": 6}, {"result": {"from": "154.54.39.129", "country": "US", "coordinates": [38.0, -97.0], "public": true, "rtt": 148.85733333333334, "asn": 174}, "hop": 7}, {"result": {"from": "130.117.51.234", "country": "EU", "coordinates": [47.0, 8.0], "public": true, "rtt": 149.71699999999998, "asn": 174}, "hop": 8}], "src_addr": "41.204.160.27", "group_id": 2493068, "type": "traceroute", "msm_name": "Traceroute", "size": 48}]