[{"lts": 39, "size": 48, "group_id": 2901789, "from": "137.158.58.151", "dst_name": "137.215.97.20", "fw": 4720, "proto": "TCP", "af": 4, "msm_name": "Traceroute", "prb_id": 18114, "result": [{"result": {"rtt": 2.1176666666666666, "from": "137.158.58.129"}, "hop": 1}, {"result": {"rtt": 0.9036666666666667, "from": "137.158.255.164"}, "hop": 2}, {"result": {"rtt": 1.168, "from": "137.158.248.21"}, "hop": 3}, {"result": {"x": "*"}, "hop": 4}, {"result": {"x": "*"}, "hop": 5}, {"result": {"x": "*"}, "hop": 6}, {"result": {"x": "*"}, "hop": 7}, {"result": {"x": "*"}, "hop": 8}, {"result": {"x": "*"}, "hop": 255}], "timestamp": 1446371981, "src_addr": "137.158.58.151", "endtime": 1446372061, "type": "traceroute", "dst_addr": "137.215.97.20", "msm_id": 2901789}]