[{"lts": 134, "size": 48, "group_id": 2803875, "from": "41.89.1.251", "dst_name": "41.93.31.1", "fw": 4700, "proto": "UDP", "af": 4, "msm_name": "Traceroute", "prb_id": 13114, "result": [{"result": {"rtt": 0.7083333333333334, "from": "41.89.1.1"}, "hop": 1}, {"result": {"rtt": 0.5516666666666666, "from": "41.204.176.121"}, "hop": 2}, {"result": {"rtt": 170.48766666666668, "from": "196.32.209.85"}, "hop": 3}, {"result": {"rtt": 314.564, "from": "196.32.209.74"}, "hop": 4}, {"result": {"rtt": 322.4346666666667, "from": "41.93.31.1"}, "hop": 5}, {"result": {"x": "*"}, "hop": 6}, {"result": {"x": "*"}, "hop": 7}, {"result": {"x": "*"}, "hop": 8}, {"result": {"x": "*"}, "hop": 9}, {"result": {"x": "*"}, "hop": 10}, {"result": {"x": "*"}, "hop": 255}], "timestamp": 1444750228, "src_addr": "41.89.1.251", "endtime": 1444750302, "type": "traceroute", "dst_addr": "41.93.31.1", "msm_id": 2803875}]