[{"lts": 116, "size": 48, "group_id": 2810857, "from": "146.231.130.254", "dst_name": "155.232.14.149", "fw": 4720, "proto": "UDP", "af": 4, "msm_name": "Traceroute", "prb_id": 18169, "result": [{"result": {"rtt": 31.825666666666667, "from": "155.232.6.233"}, "hop": 7}, {"result": {"rtt": 31.286, "from": "155.232.15.136"}, "hop": 8}, {"result": {"rtt": 31.260333333333335, "from": "155.232.6.78"}, "hop": 9}, {"result": {"rtt": 34.529, "from": "155.232.14.149"}, "hop": 10}], "timestamp": 1444827968, "src_addr": "146.231.130.254", "endtime": 1444827969, "type": "traceroute", "dst_addr": "155.232.14.149", "msm_id": 2810857}]