[{"lts": 106, "size": 48, "group_id": 2494738, "from": "41.89.1.251", "dst_name": "41.204.161.16", "fw": 4700, "proto": "ICMP", "af": 4, "msm_name": "Traceroute", "prb_id": 13114, "result": [{"result": {"rtt": 0.5176666666666666, "from": "41.89.1.1"}, "hop": 1}, {"result": {"rtt": 0.94, "from": "41.204.184.158"}, "hop": 2}, {"result": {"rtt": 1.0113333333333332, "from": "41.204.161.16"}, "hop": 3}], "timestamp": 1444379575, "src_addr": "41.89.1.251", "endtime": 1444379575, "type": "traceroute", "dst_addr": "41.204.161.16", "msm_id": 2494738}]